mod_log.py
MC/__init__.py
MC/World/__init__.py
MC/World/EntityManager/EntityManager.py
MC/World/EntityManager/__init__.py
Meta/ClassMetaManager.py
Meta/EnumMeta.py
Meta/PropertyObject.py
Meta/TypeMeta.py
Meta/__init__.py
Preset/__init__.py
Preset/Controller/PresetApi.py
Preset/Controller/__init__.py
Preset/Model/BoxData.py
Preset/Model/GameObject.py
Preset/Model/PartBase.py
Preset/Model/PresetBase.py
Preset/Model/PresetDataMeta.py
Preset/Model/SdkInterface.py
Preset/Model/Transform.py
Preset/Model/TransformObject.py
Preset/Model/__init__.py
Preset/Model/Block/BlockPreset.py
Preset/Model/Block/__init__.py
Preset/Model/Effect/EffectObject.py
Preset/Model/Effect/EffectPreset.py
Preset/Model/Effect/__init__.py
Preset/Model/Entity/EntityObject.py
Preset/Model/Entity/EntityPreset.py
Preset/Model/Entity/__init__.py
Preset/Model/Player/PlayerObject.py
Preset/Model/Player/PlayerPreset.py
Preset/Model/Player/__init__.py
Preset/Model/Textboard/TextboardObject.py
Preset/Model/Textboard/TextboardPreset.py
Preset/Model/Textboard/__init__.py
Preset/Model/UI/UIPreset.py
Preset/Model/UI/__init__.py
Preset/Parts/BasicPartSdkAttr.py
Preset/Parts/BasicPartSdkAttrMeta.py
Preset/Parts/CameraTrackPart.py
Preset/Parts/EntityBasePart.py
Preset/Parts/NavPointsPart.py
Preset/Parts/PartEvent.py
Preset/Parts/PlayerBasicPart.py
Preset/Parts/PortalPart.py
Preset/Parts/PostprocessPart.py
Preset/Parts/SkyBoxPart.py
Preset/Parts/TriggerPart.py
Preset/Parts/UseConfigPartBase.py
Preset/Parts/WorldPart.py
Preset/Parts/__init__.py
apolloCommon/__init__.py
apolloCommon/commonNetgameApi.py
apolloCommon/extraMongoPool.py
apolloCommon/extraMysqlPool.py
apolloCommon/extraRedisPool.py
apolloCommon/launcherApi.py
apolloCommon/mongoPool.py
apolloCommon/mysqlPool.py
apolloCommon/redisPool.py
apolloCommon/workerPool.py
lobby/__init__.py
lobby/netgameApi.py
lobbyGame/__init__.py
lobbyGame/netgameApi.py
lobbyGame/serverEvent.py
master/__init__.py
master/masterHttp.py
master/netgameApi.py
master/serverEvent.py
mc_netease_sdk-3.7.0.70260.dist-info/METADATA
mc_netease_sdk-3.7.0.70260.dist-info/WHEEL
mc_netease_sdk-3.7.0.70260.dist-info/top_level.txt
mc_netease_sdk-3.7.0.70260.dist-info/RECORD
