Metadata-Version: 2.1
Name: mc-netease-sdk
Version: 3.7.0.70260
Summary: Minecraft Netease Edition modAPI
Home-page: http://mc.163.com/dev/mcmanual/mc-dev/mcdocs
Author: mc_netease_sdk
Author-email: mc_sdk@163.com
License: MIT Licence
Platform: any
